pyshqg/__init__.py
pyshqg/backend/__init__.py
pyshqg/backend/abstract.py
pyshqg/backend/numpy_backend.py
pyshqg/backend/tensorflow_backend.py
pyshqg/core/__init__.py
pyshqg/core/constructors.py
pyshqg/core/dissipation.py
pyshqg/core/integration.py
pyshqg/core/model.py
pyshqg/core/poisson.py
pyshqg/core/source.py
pyshqg/core/spectral_transformations.py
pyshqg/data/data_t63.zarr/.zattrs
pyshqg/data/data_t63.zarr/.zgroup
pyshqg/data/data_t63.zarr/.zmetadata
pyshqg/data/data_t63.zarr/forcing/0.0.0
pyshqg/data/data_t63.zarr/initial_q/0.0.0
pyshqg/data/data_t63.zarr/land_sea_mask/0.0
pyshqg/data/data_t63.zarr/lat/0
pyshqg/data/data_t63.zarr/lon/0
pyshqg/data/data_t63.zarr/orography/0.0
pyshqg/data/test_t21_t31.zarr/.zattrs
pyshqg/data/test_t21_t31.zarr/.zgroup
pyshqg/data/test_t21_t31.zarr/.zmetadata
pyshqg/data/test_t21_t31.zarr/dissip_ekman/0.0.0.0
pyshqg/data/test_t21_t31.zarr/dpsi_dphi/0.0.0.0
pyshqg/data/test_t21_t31.zarr/dpsi_dtheta/0.0.0.0
pyshqg/data/test_t21_t31.zarr/dq_dphi/0.0.0.0
pyshqg/data/test_t21_t31.zarr/dq_dtheta/0.0.0.0
pyshqg/data/test_t21_t31.zarr/forcing/0.0.0
pyshqg/data/test_t21_t31.zarr/grid_dq_dt/0.0.0.0
pyshqg/data/test_t21_t31.zarr/grid_to_spec_dq_dt/0.0.0.0.0
pyshqg/data/test_t21_t31.zarr/jacobian/0.0.0.0
pyshqg/data/test_t21_t31.zarr/lat/0
pyshqg/data/test_t21_t31.zarr/lon/0
pyshqg/data/test_t21_t31.zarr/spec_abm/0.0.0.0.0
pyshqg/data/test_t21_t31.zarr/spec_dissip_sel/0.0.0.0.0
pyshqg/data/test_t21_t31.zarr/spec_dissip_therm/0.0.0.0.0
pyshqg/data/test_t21_t31.zarr/spec_dq_dt/0.0.0.0.0
pyshqg/data/test_t21_t31.zarr/spec_ee/0.0.0.0.0
pyshqg/data/test_t21_t31.zarr/spec_psi/0.0.0.0.0
pyshqg/data/test_t21_t31.zarr/spec_q/0.0.0.0.0
pyshqg/data/test_t21_t31.zarr/spec_rk2/0.0.0.0.0
pyshqg/data/test_t21_t31.zarr/spec_rk4/0.0.0.0.0
pyshqg/data/test_t21_t31.zarr/spec_tendencies/0.0.0.0.0
pyshqg/data/test_t21_t31.zarr/spec_total_q/0.0.0.0.0
pyshqg/data/test_t21_t31.zarr/zeta/0.0.0
pyshqg/data/test_t42_t63.zarr/.zattrs
pyshqg-1.0.1.dist-info/LICENSE
pyshqg-1.0.1.dist-info/METADATA
pyshqg-1.0.1.dist-info/WHEEL
pyshqg-1.0.1.dist-info/top_level.txt
pyshqg-1.0.1.dist-info/RECORD
