Metadata-Version: 2.1
Name: pyshqg
Version: 1.0.1
Summary: QG Model in spherical harmonics
Author-email: Alban Farchi <alban.farchi@enpc.fr>, Marc Bocquet <marc.bocquet@enpc.fr>, Quentin Malartic <quentin.malartic@enpc.fr>, Fabio D'Andrea <fabio.dandrea@lmd.ipsl.fr>
License: MIT
Project-URL: Documentation, https://pyshqg.readthedocs.io
Project-URL: Source, https://github.com/cerea-daml/pyshqg
Project-URL: Issues, https://github.com/cerea-daml/pyshqg/issues
Keywords: quasi-geostrophic,numerical model,atmosphere,spherical harmonics
Classifier: License :: OSI Approved :: MIT License
Classifier: Programming Language :: Python
Classifier: Programming Language :: Python :: 3
Classifier: Intended Audience :: Education
Classifier: Intended Audience :: Science/Research
Classifier: Topic :: Scientific/Engineering :: Atmospheric Science
Requires-Python: >=3.9
License-File: LICENSE
Requires-Dist: numpy
Requires-Dist: pyshtools ==4.10.4
Requires-Dist: xarray
Requires-Dist: zarr
Requires-Dist: tqdm
Provides-Extra: complete
Requires-Dist: pyshqg[dev,doc] ; extra == 'complete'
Provides-Extra: dev
Requires-Dist: pytest ; extra == 'dev'
Requires-Dist: pyyaml ; extra == 'dev'
Requires-Dist: jupyterlab ; extra == 'dev'
Requires-Dist: ipywidgets ; extra == 'dev'
Requires-Dist: matplotlib ; extra == 'dev'
Requires-Dist: cartopy ; extra == 'dev'
Requires-Dist: cmocean ; extra == 'dev'
Provides-Extra: doc
Requires-Dist: sphinx ; extra == 'doc'
Requires-Dist: sphinx-rtd-theme ; extra == 'doc'
Requires-Dist: nbsphinx ; extra == 'doc'
Requires-Dist: sphinx-gallery ; extra == 'doc'
Requires-Dist: tomli ; extra == 'doc'
Requires-Dist: m2r2 ; extra == 'doc'
Requires-Dist: ipython ; extra == 'doc'
